CHANGES.rst
MANIFEST.in
README.rst
setup.py
MoPyTools.egg-info/PKG-INFO
MoPyTools.egg-info/SOURCES.txt
MoPyTools.egg-info/dependency_links.txt
MoPyTools.egg-info/entry_points.txt
MoPyTools.egg-info/requires.txt
MoPyTools.egg-info/top_level.txt
mopytools/__init__.py
mopytools/build.py
mopytools/build_app.py
mopytools/build_rpms.py
mopytools/util.py
mopytools/tests/__init__.py
mopytools/tests/test_build.py