Metadata-Version: 1.0
Name: MoPyTools
Version: 3.3
Summary: Set of tools to build Mozilla Services apps
Home-page: https://github.com/mozilla-services/mopytools
Author: Mozilla Services
Author-email: services-dev@mozilla.org
License: UNKNOWN
Platform: UNKNOWN
